{
  "gitSyncId": "64abaf6c5b74fd62c2bf334e_64b8eedbe787d642dd2ec45e",
  "id": "KPI Monitoring_Select_emp_by_kpi",
  "pluginId": "postgres-plugin",
  "pluginType": "DB",
  "unpublishedAction": {
    "actionConfiguration": {
      "body": "SELECT emp_id\nFROM public.kpi\nWHERE kpi_id = {{Select_KPI.selectedOptionValue}};",
      "encodeParamsToggle": true,
      "paginationType": "NONE",
      "pluginSpecifiedTemplates": [
        {
          "value": true
        }
      ],
      "timeoutInMillisecond": 10000
    },
    "confirmBeforeExecute": false,
    "datasource": {
      "id": "Mock_DB_V2",
      "isAutoGenerated": false,
      "name": "Mock_DB_V2",
      "pluginId": "postgres-plugin"
    },
    "dynamicBindingPathList": [
      {
        "key": "body"
      }
    ],
    "executeOnLoad": false,
    "name": "Select_emp_by_kpi",
    "pageId": "KPI Monitoring",
    "userSetOnLoad": false
  }
}